clack/__init__.py
clack/__main__.py
clack/clack.py
clack/cli.py
clack/cmd_call.py
clack/cmd_settings.py
clack/environment.py
clack/lib_portal_api.py
clack/botrlib/__init__.py
clack/botrlib/client.py
clack_cli-1.0.0.dist-info/DESCRIPTION.rst
clack_cli-1.0.0.dist-info/entry_points.txt
clack_cli-1.0.0.dist-info/METADATA
clack_cli-1.0.0.dist-info/metadata.json
clack_cli-1.0.0.dist-info/RECORD
clack_cli-1.0.0.dist-info/top_level.txt
clack_cli-1.0.0.dist-info/WHEEL
