Metadata-Version: 2.0
Name: clack-cli
Version: 1.0.0
Summary: Clack is a Command Line API Calling Kit based on Click.
Home-page: https://github.com/rmnl/clack
Author: R Meurders
Author-email: pypi+clack@rmnl.net
License: MIT
Keywords: development command line tool api interface jwplayer
Platform: UNKNOWN
Classifier: Development Status :: 5 - Production/Stable
Classifier: Intended Audience :: Developers
Classifier: Topic :: Utilities
Classifier: License :: OSI Approved :: MIT License
Classifier: Programming Language :: Python :: 2.7
Requires-Dist: Click (>=5.0)
Requires-Dist: httplib2 (>=0.9)
Requires-Dist: urllib3 (>=1.10.1)
Requires-Dist: keyring (>=5.7.1)
